Metadata-Version: 2.1
Name: hybridset
Version: 1.0
Summary: Mutable set storing apart hashables and unhashables values
Home-page: https://gitlab.com/yahya-abou-imran/hybridset
Author: Yahya Abou Imran
Author-email: yahya-abou-imran@pm.me
License: GPLv3
Download-URL: https://gitlab.com/yahya-abou-imran/hybridset/-/archive/v1.0/archive.zip/hybridset-v1.0.zip
Platform: UNKNOWN
